LICENSE
MANIFEST.in
README.md
extra-requirements.txt
fastentrypoints.py
pyproject.toml
setup.py
cmon/__init__.py
cmon/__main__.py
cmon/_docarray.py
cmon/checker.py
cmon/constants.py
cmon/enums.py
cmon/excepts.py
cmon/exporter.py
cmon/helper.py
cmon/importer.py
cmon.pw.egg-info/PKG-INFO
cmon.pw.egg-info/SOURCES.txt
cmon.pw.egg-info/dependency_links.txt
cmon.pw.egg-info/entry_points.txt
cmon.pw.egg-info/not-zip-safe
cmon.pw.egg-info/requires.txt
cmon.pw.egg-info/top_level.txt
cmon/clients/__init__.py
cmon/clients/grpc.py
cmon/clients/helper.py
cmon/clients/http.py
cmon/clients/mixin.py
cmon/clients/websocket.py
cmon/clients/base/__init__.py
cmon/clients/base/grpc.py
cmon/clients/base/helper.py
cmon/clients/base/http.py
cmon/clients/base/retry.py
cmon/clients/base/stream_rpc.py
cmon/clients/base/unary_rpc.py
cmon/clients/base/websocket.py
cmon/clients/request/__init__.py
cmon/clients/request/asyncio.py
cmon/clients/request/helper.py
cmon/jaml/__init__.py
cmon/jaml/helper.py
cmon/jaml/parsers/__init__.py
cmon/jaml/parsers/base.py
cmon/jaml/parsers/deployment/__init__.py
cmon/jaml/parsers/deployment/legacy.py
cmon/jaml/parsers/executor/__init__.py
cmon/jaml/parsers/executor/legacy.py
cmon/jaml/parsers/flow/__init__.py
cmon/jaml/parsers/flow/v1.py
cmon/jaml/parsers/gateway/__init__.py
cmon/jaml/parsers/gateway/legacy.py
cmon/logging/__init__.py
cmon/logging/formatter.py
cmon/logging/logger.py
cmon/logging/predefined.py
cmon/logging/profile.py
cmon/orchestrate/__init__.py
cmon/orchestrate/helper.py
cmon/orchestrate/orchestrator.py
cmon/orchestrate/deployments/__init__.py
cmon/orchestrate/deployments/install_requirements_helper.py
cmon/orchestrate/deployments/config/__init__.py
cmon/orchestrate/deployments/config/docker_compose.py
cmon/orchestrate/deployments/config/helper.py
cmon/orchestrate/deployments/config/k8s.py
cmon/orchestrate/deployments/config/k8slib/__init__.py
cmon/orchestrate/deployments/config/k8slib/kubernetes_deployment.py
cmon/orchestrate/deployments/config/k8slib/kubernetes_tools.py
cmon/orchestrate/flow/__init__.py
cmon/orchestrate/flow/asyncio.py
cmon/orchestrate/flow/base.py
cmon/orchestrate/flow/builder.py
cmon/orchestrate/pods/__init__.py
